Metadata-Version: 2.1
Name: mypystarter
Version: 0.1.0
Summary: A Django JumpStart Library.
Home-page: https://github.com/jadliaissam/PyStarterV2
Author: JADLI AISSAM
Author-email: jadliaissam@gmail.com
License: MIT License
Classifier: Environment :: Web Environment
Classifier: Framework :: Django
Classifier: Intended Audience :: Developers
Classifier: License :: OSI Approved :: MIT License
Classifier: Operating System :: OS Independent
Classifier: Programming Language :: Python
Classifier: Programming Language :: Python :: 3
Classifier: Programming Language :: Python :: 3.7
Classifier: Programming Language :: Python :: 3.8
Classifier: Programming Language :: Python :: 3.9
Classifier: Programming Language :: Python :: 3.10
Classifier: Topic :: Internet :: WWW/HTTP
Classifier: Topic :: Internet :: WWW/HTTP :: Dynamic Content
Requires-Dist: asgiref >=3.7.2
Requires-Dist: attrs >=23.2.0
Requires-Dist: backports.tarfile >=1.1.1
Requires-Dist: boto3 >=1.34.59
Requires-Dist: botocore >=1.34.59
Requires-Dist: certifi >=2024.2.2
Requires-Dist: charset-normalizer >=3.3.2
Requires-Dist: Django >=5.0.2
Requires-Dist: django-cors-headers >=4.3.1
Requires-Dist: django-filter >=23.5
Requires-Dist: django-storages >=1.14.2
Requires-Dist: django-tenants >=3.6.1
Requires-Dist: djangorestframework >=3.14.0
Requires-Dist: djangorestframework-simplejwt >=5.3.1
Requires-Dist: docutils >=0.21.2
Requires-Dist: drf-yasg >=1.21.7
Requires-Dist: idna >=3.7
Requires-Dist: importlib-metadata >=7.0.0
Requires-Dist: inflection >=0.5.1
Requires-Dist: jaraco.classes >=3.4.0
Requires-Dist: jaraco.context >=5.3.0
Requires-Dist: jaraco.functools >=4.0.1
Requires-Dist: jmespath >=1.0.1
Requires-Dist: jsonschema >=4.21.1
Requires-Dist: jsonschema-specifications >=2023.12.1
Requires-Dist: keyring >=25.2.1
Requires-Dist: logtail-python >=0.2.10
Requires-Dist: loguru >=0.7.2
Requires-Dist: markdown-it-py >=3.0.0
Requires-Dist: mdurl >=0.1.2
Requires-Dist: more-itertools >=10.2.0
Requires-Dist: msgpack >=1.0.8
Requires-Dist: nh3 >=0.2.17
Requires-Dist: packaging >=23.2
Requires-Dist: pillow >=10.2.0
Requires-Dist: pkginfo >=1.10.0
Requires-Dist: psycopg2-binary >=2.9.9
Requires-Dist: Pygments >=2.18.0
Requires-Dist: PyJWT >=2.8.0
Requires-Dist: python-dateutil >=2.9.0.post0
Requires-Dist: python-decouple >=3.8
Requires-Dist: pytz >=2024.1
Requires-Dist: PyYAML >=6.0.1
Requires-Dist: readme-renderer >=42.0
Requires-Dist: referencing >=0.33.0
Requires-Dist: requests >=2.31.0
Requires-Dist: requests-toolbelt >=1.0.0
Requires-Dist: rfc3986 >=2.0.0
Requires-Dist: rich >=13.7.1
Requires-Dist: rpds-py >=0.18.0
Requires-Dist: s3transfer >=0.10.0
Requires-Dist: six >=1.16.0
Requires-Dist: sqlparse >=0.4.4
Requires-Dist: swagger-spec-validator >=3.0.3
Requires-Dist: twine >=5.1.0
Requires-Dist: typing-extensions >=4.10.0
Requires-Dist: uritemplate >=4.1.1
Requires-Dist: urllib3 >=2.0.7
Requires-Dist: zipp >=3.18.2
